odoo10_addon_document_page_environmental_aspect-10.0.1.1.0-nspkg.pth
odoo/addons/document_page_environmental_aspect/README.rst
odoo/addons/document_page_environmental_aspect/__init__.py
odoo/addons/document_page_environmental_aspect/__manifest__.py
odoo/addons/document_page_environmental_aspect/data/document_page.xml
odoo/addons/document_page_environmental_aspect/i18n/de.po
odoo/addons/document_page_environmental_aspect/i18n/document_page_environmental_aspect.pot
odoo/addons/document_page_environmental_aspect/i18n/es_CL.po
odoo/addons/document_page_environmental_aspect/i18n/fr.po
odoo/addons/document_page_environmental_aspect/i18n/nb.po
odoo/addons/document_page_environmental_aspect/i18n/pt_BR.po
odoo/addons/document_page_environmental_aspect/i18n/sl.po
odoo/addons/document_page_environmental_aspect/i18n/sv.po
odoo/addons/document_page_environmental_aspect/i18n/vi.po
odoo/addons/document_page_environmental_aspect/migrations/7.0.1.0/pre-migration.py
odoo/addons/document_page_environmental_aspect/security/environmental_aspect_security.xml
odoo/addons/document_page_environmental_aspect/static/description/icon.png
odoo/addons/document_page_environmental_aspect/views/document_page.xml
odoo10_addon_document_page_environmental_aspect-10.0.1.1.0.dist-info/METADATA
odoo10_addon_document_page_environmental_aspect-10.0.1.1.0.dist-info/WHEEL
odoo10_addon_document_page_environmental_aspect-10.0.1.1.0.dist-info/namespace_packages.txt
odoo10_addon_document_page_environmental_aspect-10.0.1.1.0.dist-info/top_level.txt
odoo10_addon_document_page_environmental_aspect-10.0.1.1.0.dist-info/RECORD
